Metadata-Version: 2.1
Name: filetest
Version: 2020.7.1
Summary: file test functions
Home-page: https://github.com/andrewp-as-is/filetest.py
License: Unlicense
Keywords: file test
Platform: UNKNOWN
Classifier: License :: Public Domain
Classifier: Operating System :: OS Independent
Classifier: Programming Language :: Python :: 3
